EVE_Gnosis/__init__.py
EVE_Gnosis/effects/__init__.py
EVE_Gnosis/effects/adaptivearmorhardener.py
EVE_Gnosis/formulas/__init__.py
EVE_Gnosis/formulas/formulas.py
EVE_Gnosis/simulations/__init__.py
EVE_Gnosis/simulations/capacitor.py
EVE_Gnosis-2017.6.27.dist-info/DESCRIPTION.rst
EVE_Gnosis-2017.6.27.dist-info/METADATA
EVE_Gnosis-2017.6.27.dist-info/RECORD
EVE_Gnosis-2017.6.27.dist-info/WHEEL
EVE_Gnosis-2017.6.27.dist-info/metadata.json
EVE_Gnosis-2017.6.27.dist-info/top_level.txt
