Metadata-Version: 2.0
Name: EVE-Gnosis
Version: 2017.6.27
Summary: EVE Online Formulas and Simulations
Home-page: https://github.com/Pyfa-fit/EVE_Gnosis
Author: Ebag Trescientas
Author-email: ebagola@gmail.com
License: UNKNOWN
Platform: UNKNOWN
